serpnode/__init__.py
serpnode/client.py
serpnode-0.1.2.dist-info/METADATA
serpnode-0.1.2.dist-info/WHEEL
serpnode-0.1.2.dist-info/top_level.txt
serpnode-0.1.2.dist-info/RECORD
