Metadata-Version: 2.4
Name: serpnode
Version: 0.1.2
Summary: Serpnode.com API client for Python
Author-email: Your Name <you@example.com>
License: MIT
Project-URL: Homepage, https://serpnode.com/
Project-URL: Repository, https://github.com/everapihq/serpnode-python
Project-URL: Issues, https://github.com/everapihq/serpnode-python/issues
Keywords: serp,search,google,api,client,serpnode
Requires-Python: >=3.8
Requires-Dist: requests>=2.28
